drn/__init__.py
drn/interpretability.py
drn/metrics.py
drn/py.typed
drn/train.py
drn/distributions/__init__.py
drn/distributions/extended_histogram.py
drn/distributions/histogram.py
drn/models/__init__.py
drn/models/cann.py
drn/models/ddr.py
drn/models/drn.py
drn/models/glm.py
drn/models/mdn.py
drn-0.0.1.dist-info/METADATA
drn-0.0.1.dist-info/WHEEL
drn-0.0.1.dist-info/licenses/LICENSE.md
drn-0.0.1.dist-info/RECORD
