Metadata-Version: 2.4
Name: drn
Version: 0.0.1
Summary: Distributional regression modelling using PyTorch
Author-email: Eric Dong <tiandong1999@gmail.com>, Patrick Laub <patrick.laub@gmail.com>
Maintainer-email: Eric Dong <tiandong1999@gmail.com>
License-File: LICENSE.md
Classifier: License :: OSI Approved :: MIT License
Classifier: Programming Language :: Python :: 3
Requires-Python: >=3.8
Requires-Dist: matplotlib
Requires-Dist: numpy
Requires-Dist: pandas
Requires-Dist: scikit-learn
Requires-Dist: seaborn
Requires-Dist: shap
Requires-Dist: statsmodels
Requires-Dist: torch
Requires-Dist: tqdm
Provides-Extra: dev
Requires-Dist: black; extra == 'dev'
Requires-Dist: ipykernel; extra == 'dev'
Requires-Dist: isort; extra == 'dev'
Requires-Dist: jupytext; extra == 'dev'
Requires-Dist: mypy; extra == 'dev'
Requires-Dist: pre-commit; extra == 'dev'
Requires-Dist: pytest; extra == 'dev'
